algobowl/__init__.py
algobowl/model.py
algobowl/cli/__init__.py
algobowl/cli/__main__.py
algobowl/cli/admin.py
algobowl/cli/auth.py
algobowl/cli/config.py
algobowl/cli/formatter.py
algobowl/cli/group.py
algobowl/cli/problem.py
algobowl/config/__init__.py
algobowl/config/app_cfg.py
algobowl/config/auth.py
algobowl/config/environment.py
algobowl/config/middleware.py
algobowl/controllers/__init__.py
algobowl/controllers/competition.py
algobowl/controllers/error.py
algobowl/controllers/file_redirector.py
algobowl/controllers/group.py
algobowl/controllers/pref.py
algobowl/controllers/root.py
algobowl/controllers/setup.py
algobowl/controllers/api/__init__.py
algobowl/controllers/api/user.py
algobowl/lib/__init__.py
algobowl/lib/algocdn.py
algobowl/lib/app_globals.py
algobowl/lib/base.py
algobowl/lib/constants.py
algobowl/lib/helpers.py
algobowl/lib/logoutput.py
algobowl/lib/problem.py
algobowl/lib/problem_tester.py
algobowl/templates/__init__.py
algobowl/templates/cli_setup.xhtml
algobowl/templates/edu_landing.xhtml
algobowl/templates/error.xhtml
algobowl/templates/index.xhtml
algobowl/templates/logoutput.xhtml
algobowl/templates/master.xhtml
algobowl/templates/nonedu_landing.xhtml
algobowl/templates/privacy.xhtml
algobowl/templates/tos.xhtml
algobowl/templates/admin/__init__.py
algobowl/templates/admin/edit.xhtml
algobowl/templates/admin/get_all.xhtml
algobowl/templates/admin/index.xhtml
algobowl/templates/admin/new.xhtml
algobowl/templates/competition/__init__.py
algobowl/templates/competition/archive.xhtml
algobowl/templates/competition/grade.xhtml
algobowl/templates/competition/list.xhtml
algobowl/templates/competition/ov.xhtml
algobowl/templates/competition/rankings.xhtml
algobowl/templates/group/__init__.py
algobowl/templates/group/evaluation.xhtml
algobowl/templates/group/index.xhtml
algobowl/templates/group/input_upload.xhtml
algobowl/templates/group/output_upload.xhtml
algobowl/templates/group/resolution.xhtml
algobowl/templates/group/select.xhtml
algobowl-2025.8.31.0.dist-info/licenses/LICENSE
algobowl-2025.8.31.0.dist-info/METADATA
algobowl-2025.8.31.0.dist-info/WHEEL
algobowl-2025.8.31.0.dist-info/entry_points.txt
algobowl-2025.8.31.0.dist-info/top_level.txt
algobowl-2025.8.31.0.dist-info/RECORD
