Metadata-Version: 2.4
Name: algobowl
Version: 2025.8.31.0
Summary: Competition-based group project for Algorithms courses
Home-page: https://github.com/jackrosenthal/algobowl
Author: Jack Rosenthal
Author-email: jack@rosenth.al
Requires-Python: >=3.9,<4
License-File: LICENSE
Requires-Dist: click>=8.0
Requires-Dist: pytest>=4.6
Requires-Dist: pytest-cov>=4.1.0
Requires-Dist: requests>=2.0
Requires-Dist: tabulate>=0.8
Requires-Dist: toml>=0.10
Requires-Dist: typing-extensions
Provides-Extra: web
Requires-Dist: TurboGears2==2.4.3; extra == "web"
Requires-Dist: tgext.admin-jmr; extra == "web"
Requires-Dist: decorator; extra == "web"
Requires-Dist: google-api-python-client; extra == "web"
Requires-Dist: google-auth-oauthlib; extra == "web"
Requires-Dist: tw2.forms; extra == "web"
Requires-Dist: Beaker>=1.8.0; extra == "web"
Requires-Dist: Kajiki>=0.6.3; extra == "web"
Requires-Dist: filedepot>=0.6.0; extra == "web"
Requires-Dist: zope.sqlalchemy>=1.2; extra == "web"
Requires-Dist: sqlalchemy<1.4,>=1.3; extra == "web"
Requires-Dist: alembic>=0.8.8; extra == "web"
Requires-Dist: repoze.who==3.0.0; extra == "web"
Requires-Dist: WebHelpers2; extra == "web"
Requires-Dist: requests; extra == "web"
Provides-Extra: dev
Requires-Dist: TurboGears2==2.4.3; extra == "dev"
Requires-Dist: tgext.admin-jmr; extra == "dev"
Requires-Dist: decorator; extra == "dev"
Requires-Dist: google-api-python-client; extra == "dev"
Requires-Dist: google-auth-oauthlib; extra == "dev"
Requires-Dist: tw2.forms; extra == "dev"
Requires-Dist: Beaker>=1.8.0; extra == "dev"
Requires-Dist: Kajiki>=0.6.3; extra == "dev"
Requires-Dist: filedepot>=0.6.0; extra == "dev"
Requires-Dist: zope.sqlalchemy>=1.2; extra == "dev"
Requires-Dist: sqlalchemy<1.4,>=1.3; extra == "dev"
Requires-Dist: alembic>=0.8.8; extra == "dev"
Requires-Dist: repoze.who==3.0.0; extra == "dev"
Requires-Dist: WebHelpers2; extra == "dev"
Requires-Dist: requests; extra == "dev"
Requires-Dist: setuptools<80,>=79; extra == "dev"
Requires-Dist: tg.devtools==2.4.3; extra == "dev"
Dynamic: author
Dynamic: author-email
Dynamic: description
Dynamic: description-content-type
Dynamic: home-page
Dynamic: license-file
Dynamic: provides-extra
Dynamic: requires-dist
Dynamic: requires-python
Dynamic: summary
